cerbos_fastmcp/__init__.py
cerbos_fastmcp/middleware.py
cerbos_fastmcp/py.typed
cerbos_fastmcp/examples/__init__.py
cerbos_fastmcp/examples/server.py
cerbos_fastmcp-0.1.1.dist-info/licenses/LICENSE
cerbos_fastmcp-0.1.1.dist-info/METADATA
cerbos_fastmcp-0.1.1.dist-info/WHEEL
cerbos_fastmcp-0.1.1.dist-info/top_level.txt
cerbos_fastmcp-0.1.1.dist-info/RECORD
