Metadata-Version: 2.4
Name: cerbos-fastmcp
Version: 0.1.1
Summary: Cerbos authorization middleware for FastMCP servers.
Author: Cerbos
License: Apache-2.0
Project-URL: Homepage, https://cerbos.dev
Project-URL: Repository, https://github.com/cerbos/cerbos-fastmcp
Project-URL: Issues, https://github.com/cerbos/cerbos-fastmcp/issues
Project-URL: Documentation, https://docs.cerbos.dev
Keywords: cerbos,fastmcp,middleware,authorization,mcp
Classifier: Development Status :: 3 - Alpha
Classifier: Intended Audience :: Developers
Classifier: License :: OSI Approved :: Apache Software License
Classifier: Programming Language :: Python
Classifier: Programming Language :: Python :: 3
Classifier: Programming Language :: Python :: 3 :: Only
Classifier: Programming Language :: Python :: 3.11
Classifier: Programming Language :: Python :: 3.12
Classifier: Topic :: Security
Classifier: Topic :: Software Development :: Libraries :: Python Modules
Requires-Python: >=3.11
License-File: LICENSE
Requires-Dist: cerbos>=0.14.0
Requires-Dist: fastmcp>=2.12.3
Provides-Extra: dev
Requires-Dist: black>=25.9.0; extra == "dev"
Requires-Dist: pytest>=8.3.0; extra == "dev"
Requires-Dist: pytest-asyncio>=0.23.8; extra == "dev"
Dynamic: license-file
